{
            "now": "now",
            "meeting_room": "Meeting Room",
            "room_available": "Room available",
            "tap_here_to_reserve": "Tap here to reserve for 15 minutes",
            "insufficient_time_to_reserve": "INSUFFICIENT TIME TO RESERVE",
            "you_can_reserve_this_room_using_outlook": "YOU CAN RESERVE THIS ROOM USING OUTLOOK",
            "available": "Available",
            "occupied": "Occupied",
            "reserve": "Reserve",
            "reserving_room": "Reserving room",
            "tap_to_cancel": "Tap to cancel",
            "reserved_for_15_minutes": "Reserved for 15 minutes",
            "and": "and",
            "other": "other",
            "others": "others",
            "min": "min",
            "m15": "15min",
            "m30": "30min",
            "m45": "45min",
            "m60": "60min",
            "cancelling": "Cancelling..",
            "check_in": "CHECK IN",
            "remaining": " remaining",
            "end_early": "END EARLY",
            "find_a_room": "Find a Room",
            "are_you_sure_you_want_to_end_early": "Are you sure you want to end early?",
            "private_appointment": "Private Appointment",
            "daysOfWeek": ["Sunday","Monday","Tuesday","Wednesday","Thursday","Friday","Saturday"],
            "months": ["January", "February", "March", "April", "May", "June", "July", "August", "September", "October", "November", "December"]
        }
