{
    "maintenant": "maintenant",
    "meeting_room": "Salle de réunion",
    "room_available": "Chambre disponible",
    "tap_here_to_reserve": "Tapez ici pour réserver pendant 15 minutes",
    "insuffisance_time_to_reserve": "TEMPS INSUFFISANT POUR RÉSERVER",
    "you_can_reserve_this_room_using_outlook": "VOUS POUVEZ RÉSERVER CETTE PIÈCE EN UTILISANT DES PERSPECTIVES",
    "disponible": "disponible",
    "occupé": "Occupé",
    "réserve": "Réserve",
    "reserving_room": "Salle de réservation",
    "tap_to_cancel": "Appuyer pour annuler",
    "reserved_for_15_minutes": "Réservé pour 15 minutes",
    "et": "et",
    "autre": "autre",
    "autres": "autres",
    "min": "min",
    "m15": "15min",
    "m30": "30min",
    "m45": "45min",
    "m60": "60min",
    "annulation": "Annulation ..",
    "private_appointment": "Rendez-vous privé",
    "daysOfWeek": ["Dimanche", "Lundi", "Mardi", "Mercredi", "Jeudi", "Vendredi", "Samedi"],
    "mois": ["Janvier", "Février", "Mars", "Avril", "Mai", "Juin", "Juillet", "Août", "Septembre", "Octobre", "Novembre", " Décembre"]
}