{
    "now": "inmiddels",
    "meeting_room": "Vergaderzaal",
    "room_available": "Beschikbare kamer",
    "tap_here_to_reserve": "Klik hier om te reserveren voor 15 minuten",
    "insufficient_time_to_reserve": "Onvoldoende tijd om te reserveren",
    "you_can_reserve_this_room_using_outlook": "U kunt deze kamer via Outlook reserveren",
    "available": "Beschikbaar",
    "occupied": "Bewoond",
    "reserve": "Reserve",
    "reserving_room": "Reserveringsruimte",
    "tap_to_cancel": "Klik op annuleren",
    "reserved_for_15_minutes": "Gereserveerd voor 15 minuten",
    "and": "en",
    "other": "ander",
    "others": "anderen",
    "min": "notulen",
    "m15": "15",
    "m30": "30",
    "m45": "45",
    "m60": "60",
    "cancelling": "Annulering..",
    "private_appointment": "Particuliere benoeming",
    "daysOfWeek": ["Zondag","maandag","dinsdag","woensdag","donderdag","vrijdag","zaterdag"],
    "months": ["Januari", "februari", "maart", "april", "mei", "juni", "juli", "augustus", "september", "oktober", "november", "december"]
}